Workbook

Sheet Summary
A1: Corporate Credit Portfolio - Summary & Watchlist
A2: All figures from SEC EDGAR XBRL filings. Covenant thresholds are stated assumptions (see Assumptions tab), not real negotiated terms.
A4: Ticker | B4: Company | C4: Period end | D4: Internal grade | E4: PD proxy band | F4: Watchlist | G4: Revenue TTM | H4: EBITDA TTM | I4: Op margin | J4: Total debt | K4: Net debt | L4: Debt/EBITDA | M4: Net debt/EBITDA | N4: EBITDA/interest | O4: FCF TTM | P4: FCF/debt | Q4: Current ratio | R4: Quick ratio | S4: Working capital | T4: Altman Z" | U4: Z" zone | V4: Debt due <1y | W4: Data coverage | X4: Covenant headroom (turns) | Y4: Covenant status
A5: W | B5: Wayfair Inc. | C5: 46203 | D5: B | E5: High | F5: High | G5: 12904000000 | H5: 492000000 | I5: 0.0166615 | J5: 2797000000 | K5: 1654000000 | L5: 5.6849593 | M5: 3.3617886 | N5: 3.3931034 | O5: 562000000 | P5: 0.20092957 | Q5: 0.74294533 | R5: 0.70590829 | S5: -583000000 | T5: -6.7025358 | U5: Distress | W5: 1 | X5: =IF(ISBLANK(L5),"n/a",Assumptions!$C$5-L5) | Y5: =IF(ISBLANK(L5),"no data",IF(L5>Assumptions!$C$5,"BREACH","Compliant"))
A6: BBWI | B6: Bath & Body Works, Inc. | C6: 46144 | D6: BB | E6: Medium | F6: Medium | G6: 7245000000 | H6: 1399000000 | I6: 0.15845411 | J6: 3613000000 | K6: 2793000000 | L6: 2.582559 | M6: 1.996426 | N6: 5.1245421 | O6: 909000000 | P6: 0.25159148 | Q6: 1.379085 | R6: 0.81118373 | S6: 522000000 | T6: 1.2008483 | U6: Grey | V6: 0.072522983 | W6: 1 | X6: =IF(ISBLANK(L6),"n/a",Assumptions!$C$5-L6) | Y6: =IF(ISBLANK(L6),"no data",IF(L6>Assumptions!$C$5,"BREACH","Compliant"))
A7: TGT | B7: TARGET CORP | C7: 46144 | D7: BBB | E7: Medium | F7: Medium | G7: 106377000000 | H7: 7940000000 | I7: 0.044934525 | J7: 15415000000 | K7: 7270000000 | L7: 1.9414358 | M7: 0.91561713 | N7: 17.762864 | O7: 3031000000 | P7: 0.19662666 | Q7: 0.93195419 | R7: 0.29653322 | S7: -1319000000 | T7: 1.3550302 | U7: Grey | V7: 0.13792152 | W7: 1 | X7: =IF(ISBLANK(L7),"n/a",Assumptions!$C$5-L7) | Y7: =IF(ISBLANK(L7),"no data",IF(L7>Assumptions!$C$5,"BREACH","Compliant"))
A8: BURL | B8: Burlington Stores, Inc. | C8: 46144 | D8: BBB | E8: Medium | F8: Clear | G8: 11901842000 | H8: 1310105000 | I8: 0.073888563 | J8: 1917363000 | K8: 1170008000 | L8: 1.4635186 | M8: 0.8930643 | N8: 18.265413 | O8: 382940000 | P8: 0.19972222 | Q8: 1.1638641 | R8: 0.49290482 | S8: 352709000 | T8: 1.8216772 | U8: Grey | V8: 0.0086429038 | W8: 1 | X8: =IF(ISBLANK(L8),"n/a",Assumptions!$C$5-L8) | Y8: =IF(ISBLANK(L8),"no data",IF(L8>Assumptions!$C$5,"BREACH","Compliant"))
A9: M | B9: Macy's, Inc. | C9: 46144 | D9: A | E9: Low | F9: Clear | G9: 21846000000 | H9: 1933000000 | I9: 0.047972169 | J9: 2432000000 | K9: 1138000000 | L9: 1.258148 | M9: 0.58872219 | N9: 20.347368 | O9: 1425000000 | P9: 0.5859375 | Q9: 1.4753958 | R9: 0.44137783 | S9: 2222000000 | T9: 3.1563457 | U9: Safe | V9: 0.013928718 | W9: 1 | X9: =IF(ISBLANK(L9),"n/a",Assumptions!$C$5-L9) | Y9: =IF(ISBLANK(L9),"no data",IF(L9>Assumptions!$C$5,"BREACH","Compliant"))
A10: DKS | B10: DICK'S SPORTING GOODS, INC. | C10: 46144 | D10: AA | E10: Low | F10: Medium | G10: 19204947000 | H10: 1725022000 | I10: 0.061465517 | J10: 1905810000 | K10: 907582000 | L10: 1.1048033 | M10: 0.52612778 | N10: 24.761674 | O10: 402619000 | P10: 0.21125873 | Q10: 1.5008652 | R10: 0.38211569 | S10: 2426286000 | T10: 3.1047852 | U10: Safe | W10: 1 | X10: =IF(ISBLANK(L10),"n/a",Assumptions!$C$5-L10) | Y10: =IF(ISBLANK(L10),"no data",IF(L10>Assumptions!$C$5,"BREACH","Compliant"))
A11: KSS | B11: KOHLS Corp | C11: 46144 | D11: BBB | E11: Medium | F11: Clear | G11: 15461000000 | H11: 1309000000 | I11: 0.03945411 | J11: 1387000000 | K11: 958000000 | L11: 1.0595875 | M11: 0.73185638 | N11: 4.76 | O11: 1052000000 | P11: 0.75847152 | Q11: 1.4815416 | R11: 0.30628803 | S11: 1187000000 | T11: 1.6609809 | U11: Grey | W11: 1 | X11: =IF(ISBLANK(L11),"n/a",Assumptions!$C$5-L11) | Y11: =IF(ISBLANK(L11),"no data",IF(L11>Assumptions!$C$5,"BREACH","Compliant"))
A12: GAP | B12: GAP INC | C12: 46144 | D12: AA | E12: Low | F12: Clear | G12: 15400000000 | H12: 1803000000 | I12: 0.084415584 | J12: 1492000000 | K12: -1069000000 | L12: 0.82750971 | M12: -0.59290072 | N12: 19.597826 | O12: 1124000000 | P12: 0.75335121 | Q12: 1.805929 | R12: 1.0837642 | S12: 2338000000 | T12: 3.403418 | U12: Safe | W12: 1 | X12: =IF(ISBLANK(L12),"n/a",Assumptions!$C$5-L12) | Y12: =IF(ISBLANK(L12),"no data",IF(L12>Assumptions!$C$5,"BREACH","Compliant"))
A13: BBY | B13: BEST BUY CO INC | C13: 46144 | D13: A | E13: Low | F13: Clear | G13: 41860000000 | H13: 2354000000 | I13: 0.036789298 | J13: 1169000000 | K13: -580000000 | L13: 0.49660153 | M13: -0.24638912 | N13: 51.173913 | O13: 1605000000 | P13: 1.3729683 | Q13: 1.120944 | R13: 0.4029755 | S13: 943000000 | T13: 1.9707403 | U13: Grey | W13: 1 | X13: =IF(ISBLANK(L13),"n/a",Assumptions!$C$5-L13) | Y13: =IF(ISBLANK(L13),"no data",IF(L13>Assumptions!$C$5,"BREACH","Compliant"))
A14: TJX | B14: TJX COMPANIES INC /DE/ | C14: 46144 | D14: A | E14: Low | F14: Medium | G14: 61584000000 | H14: 8835000000 | I14: 0.1225643 | J14: 2870000000 | K14: -2710000000 | L14: 0.32484437 | M14: -0.30673458 | O14: 5477000000 | P14: 1.9083624 | Q14: 1.1388565 | R14: 0.54181252 | S14: 1785000000 | T14: 3.0225219 | U14: Safe | V14: 0.3471017 | W14: 1 | X14: =IF(ISBLANK(L14),"n/a",Assumptions!$C$5-L14) | Y14: =IF(ISBLANK(L14),"no data",IF(L14>Assumptions!$C$5,"BREACH","Compliant"))
A15: ROST | B15: ROSS STORES, INC. | C15: 46144 | D15: AA | E15: Low | F15: Clear | G15: 23776064000 | H15: 3430965000 | I15: 0.12217804 | J15: 1018187000 | K15: -3112793000 | L15: 0.29676403 | M15: -0.90726457 | O15: 2632326000 | P15: 2.585307 | Q15: 1.5409242 | R15: 0.93521803 | S15: 2658564000 | T15: 4.1233192 | U15: Safe | W15: 1 | X15: =IF(ISBLANK(L15),"n/a",Assumptions!$C$5-L15) | Y15: =IF(ISBLANK(L15),"no data",IF(L15>Assumptions!$C$5,"BREACH","Compliant"))
A16: ANF | B16: ABERCROMBIE & FITCH CO /DE/ | C16: 46144 | D16: AA | E16: Low | F16: Clear | G16: 5282802000 | H16: 845156000 | I16: 0.12993237 | J16: 0 | K16: -594080000 | L16: 0 | M16: -0.70292348 | O16: 416047000 | Q16: 1.448299 | R16: 0.9031335 | S16: 438041000 | T16: 6.3924531 | U16: Safe | W16: 1 | X16: =IF(ISBLANK(L16),"n/a",Assumptions!$C$5-L16) | Y16: =IF(ISBLANK(L16),"no data",IF(L16>Assumptions!$C$5,"BREACH","Compliant"))
A18: Watchlist triggers by name (Level = breach today, Trend = deteriorating, Stress = breaches under scenario):
A19: W: Debt/EBITDA 5.68x above assumed 4.5x covenant | Current ratio 0.74x below 1.0x | Altman Z" -6.70 in distress zone (below 1.1) | Working capital down 44.0% YoY (trigger 20%) | Coverage falls to 0.72x under EBITDA margin -300bps | Coverage falls to 0.52x under Combined recession
A20: BBWI: Operating margin down 169bps YoY (trigger 150bps)
A21: TGT: Current ratio 0.93x below 1.0x
A22: DKS: Operating margin down 495bps YoY (trigger 150bps) | Interest coverage down 33.7% YoY (trigger 25%)
A23: TJX: 35% of debt matures within 12 months - refinancing concentration (trigger 25%)

Sheet Company Detail
A1: Company Underwriting Detail
A2: One page per name: current position, eight-quarter trend, stress results and the triggers driving the recommendation.
A4: GAP - GAP INC | D4: Strongest credit in the portfolio
A5: Recommendation: | B5: APPROVE - within all stated credit policy thresholds
A6: Internal grade: | B6: AA (PD proxy band: Low; scorecard 0.00 on a 0=best / 2=worst scale)
A8: Metric | B8: Actual | C8: Policy threshold
A9: Revenue TTM | B9: 15400000000 | C9: -
A10: EBITDA TTM | B10: 1803000000 | C10: -
A11: Operating margin | B11: 0.084415584 | C11: -
A12: Total debt | B12: 1492000000 | C12: -
A13: Debt/EBITDA | B13: 0.82750971 | C13: <= 4.5x
A14: Net debt/EBITDA | B14: -0.59290072 | C14: -
A15: EBITDA/interest | B15: 19.597826 | C15: >= 2.0x
A16: FCF/debt | B16: 0.75335121 | C16: >= 5%
A17: Current ratio | B17: 1.805929 | C17: >= 1.0x
A18: Quick ratio | B18: 1.0837642 | C18: -
A19: Altman Z" | B19: 3.403418 | C19: >= 1.1
A21: Eight-quarter trend
A22: Metric | B22: 2024-08-03 | C22: 2024-11-02 | D22: 2025-02-01 | E22: 2025-05-03 | F22: 2025-08-02 | G22: 2025-11-01 | H22: 2026-01-31 | I22: 2026-05-02
A23: altman_z_double_prime | B23: 2.5758594 | C23: 2.7760606 | D23: 2.9345287 | E23: 3.1464131 | F23: 3.1286625 | G23: 3.2352193 | H23: 3.262576 | I23: 3.403418
A24: current_ratio | B24: 1.4916253 | C24: 1.5428571 | D24: 1.597973 | E24: 1.7112824 | F24: 1.6818893 | G24: 1.7200366 | H24: 1.7506061 | I24: 1.805929
A25: debt_to_ebitda | B25: 1.0170765 | C25: 0.95083014 | D25: 0.92431762 | E25: 0.89543269 | F25: 0.89711191 | G25: 0.90803898 | H25: 0.92613284 | I25: 0.82750971
A26: ebitda_ttm | B26: 1464000000 | C26: 1566000000 | D26: 1612000000 | E26: 1664000000 | F26: 1662000000 | G26: 1642000000 | H26: 1611000000 | I26: 1803000000
A27: fcf_ttm | B27: 1180000000 | C27: 1108000000 | D27: 1039000000 | E27: 879000000 | F27: 769000000 | G27: 779000000 | H27: 823000000 | I27: 1124000000
A28: interest_coverage | B28: 15.092784 | C28: 17.021739 | D28: 18.528736 | E28: 18.696629 | F28: 18.886364 | G28: 18.659091 | H28: 17.322581 | I28: 19.597826
A29: operating_margin | B29: 0.063402096 | C29: 0.070036101 | D29: 0.073710725 | E29: 0.076973814 | F29: 0.0768825 | G29: 0.074939459 | H29: 0.072562801 | I29: 0.084415584
A30: quick_ratio | B30: 0.83808933 | C30: 0.84180451 | D30: 0.96314496 | E30: 0.97652418 | F30: 0.96434157 | G30: 0.97011284 | H30: 1.0818182 | I30: 1.0837642
A31: working_capital | B31: 1585000000 | C31: 1805000000 | D31: 1947000000 | E31: 2030000000 | F31: 2180000000 | G31: 2361000000 | H31: 2477000000 | I31: 2338000000
A33: Stress scenarios
A34: Scenario | B34: Stressed EBITDA | C34: Debt/EBITDA | D34: EBITDA/interest | E34: FCF/debt | F34: Quick ratio
A35: Baseline (as reported) | B35: 1803000000 | C35: 0.82750971 | D35: 19.597826 | E35: 0.75335121 | F35: 1.0837642
A36: Revenue -10% | B36: 1622700000 | C36: 0.91945523 | D36: 17.638043 | E36: 0.6808445 | F36: 1.0837642
A37: Revenue -20% | B37: 1442400000 | C37: 1.0343871 | D37: 15.678261 | E37: 0.6083378 | F37: 1.0837642
A38: EBITDA margin -300bps | B38: 1341000000 | C38: 1.1126025 | D38: 14.576087 | E38: 0.56756032 | F38: 1.0837642
A39: Rates +200bps | B39: 1803000000 | C39: 0.82750971 | D39: 16.863075 | E39: 0.74585121 | F39: 1.0837642
A40: Inventory +30% (cash funded) | B40: 1803000000 | C40: 0.82750971 | D40: 19.597826 | E40: 0.33210456 | F40: 0.86711479
A41: Combined recession | B41: 1139850000 | C41: 1.3089442 | D41: 10.660774 | E41: 0.057922252 | F41: 0.86711479
A43: Triggers
A44: - nan
A47: TGT - TARGET CORP | D47: Borderline / on watchlist
A48: Recommendation: | B48: APPROVE WITH CONDITIONS - monitor quarterly against triggers below
A49: Internal grade: | B49: BBB (PD proxy band: Medium; scorecard 0.60 on a 0=best / 2=worst scale)
A51: Metric | B51: Actual | C51: Policy threshold
A52: Revenue TTM | B52: 106377000000 | C52: -
A53: EBITDA TTM | B53: 7940000000 | C53: -
A54: Operating margin | B54: 0.044934525 | C54: -
A55: Total debt | B55: 15415000000 | C55: -
A56: Debt/EBITDA | B56: 1.9414358 | C56: <= 4.5x
A57: Net debt/EBITDA | B57: 0.91561713 | C57: -
A58: EBITDA/interest | B58: 17.762864 | C58: >= 2.0x
A59: FCF/debt | B59: 0.19662666 | C59: >= 5%
A60: Current ratio | B60: 0.93195419 | C60: >= 1.0x
A61: Quick ratio | B61: 0.29653322 | C61: -
A62: Altman Z" | B62: 1.3550302 | C62: >= 1.1
A64: Eight-quarter trend
A65: Metric | B65: 2024-08-03 | C65: 2024-11-02 | D65: 2025-02-01 | E65: 2025-05-03 | F65: 2025-08-02 | G65: 2025-11-01 | H65: 2026-01-31 | I65: 2026-05-02
A66: altman_z_double_prime | B66: 1.3235806 | C66: 1.3374884 | D66: 1.3085341 | E66: 1.4085752 | F66: 1.4841857 | G66: 1.3666779 | H66: 1.3441688 | I66: 1.3550302
A67: current_ratio | B67: 0.89661729 | C67: 0.94319016 | D67: 0.93533343 | E67: 0.93512717 | F67: 0.99016803 | G67: 0.97457866 | H67: 0.94229863 | I67: 0.93195419
A68: debt_to_ebitda | B68: 1.694626 | C68: 1.7940054 | D68: 1.8649819 | E68: 1.7598954 | F68: 1.9355446 | G68: 1.9875919 | H68: 1.9944249 | I68: 1.9414358
A69: ebitda_ttm | B69: 9025000000 | C69: 8908000000 | D69: 8547000000 | E69: 8792000000 | F69: 8502000000 | G69: 8301000000 | H69: 8251000000 | I69: 7940000000
A70: fcf_ttm | B70: 5268000000 | C70: 4545000000 | D70: 4476000000 | E70: 3534000000 | F70: 2944000000 | G70: 3009000000 | H70: 2835000000 | I70: 3031000000
A71: interest_coverage | B71: 20.988372 | C71: 20.813084 | D71: 20.79562 | E71: 20.88361 | F71: 19.911007 | G71: 18.995423 | H71: 18.5 | I71: 17.762864
A72: operating_margin | B72: 0.056971109 | C72: 0.055442967 | D72: 0.052230543 | E72: 0.054230693 | F72: 0.051344188 | G72: 0.049447939 | H72: 0.048835656 | I72: 0.044934525
A73: quick_ratio | B73: 0.26591273 | C73: 0.24729258 | D73: 0.32280398 | E73: 0.24806487 | F73: 0.32008531 | G73: 0.27332643 | H73: 0.3627414 | I73: 0.29653322
A74: working_capital | B74: -2066000000 | C74: -1238000000 | D74: -1345000000 | E74: -1232000000 | F74: -189000000 | G74: -540000000 | H74: -1225000000 | I74: -1319000000
A76: Stress scenarios
A77: Scenario | B77: Stressed EBITDA | C77: Debt/EBITDA | D77: EBITDA/interest | E77: FCF/debt | F77: Quick ratio
A78: Baseline (as reported) | B78: 7940000000 | C78: 1.9414358 | D78: 17.762864 | E78: 0.19662666 | F78: 0.29653322
A79: Revenue -10% | B79: 7146000000 | C79: 2.1571509 | D79: 15.986577 | E79: 0.1657217 | F79: 0.29653322
A80: Revenue -20% | B80: 6352000000 | C80: 2.4267947 | D80: 14.210291 | E80: 0.13481674 | F80: 0.29653322
A81: EBITDA margin -300bps | B81: 4.74869e+09 | C81: 3.2461584 | D81: 10.623468 | E81: 0.072410898 | F81: 0.29653322
A82: Rates +200bps | B82: 7940000000 | C82: 1.9414358 | D82: 13.208018 | E82: 0.18912666 | F82: 0.29653322
A83: Inventory +30% (cash funded) | B83: 7940000000 | C83: 1.9414358 | D83: 17.762864 | E83: -0.043081414 | F83: 0.10590693
A84: Combined recession | B84: 4.0363865e+09 | C84: 3.8190099 | D84: 6.7144415 | E84: -0.20252226 | F84: 0.10590693
A86: Triggers
A87: - Current ratio 0.93x below 1.0x
A90: W - Wayfair Inc. | D90: Weakest credit in the portfolio
A91: Recommendation: | B91: REJECT / REMEDIATE - outside credit policy today
A92: Internal grade: | B92: B (PD proxy band: High; scorecard 1.35 on a 0=best / 2=worst scale)
A94: Metric | B94: Actual | C94: Policy threshold
A95: Revenue TTM | B95: 12904000000 | C95: -
A96: EBITDA TTM | B96: 492000000 | C96: -
A97: Operating margin | B97: 0.0166615 | C97: -
A98: Total debt | B98: 2797000000 | C98: -
A99: Debt/EBITDA | B99: 5.6849593 | C99: <= 4.5x
A100: Net debt/EBITDA | B100: 3.3617886 | C100: -
A101: EBITDA/interest | B101: 3.3931034 | C101: >= 2.0x
A102: FCF/debt | B102: 0.20092957 | C102: >= 5%
A103: Current ratio | B103: 0.74294533 | C103: >= 1.0x
A104: Quick ratio | B104: 0.70590829 | C104: -
A105: Altman Z" | B105: -6.7025358 | C105: >= 1.1
A107: Eight-quarter trend
A108: Metric | B108: 2024-09-30 | C108: 2024-12-31 | D108: 2025-03-31 | E108: 2025-06-30 | F108: 2025-09-30 | G108: 2025-12-31 | H108: 2026-03-31 | I108: 2026-06-30
A109: altman_z_double_prime | B109: -6.3528246 | C109: -6.5466431 | D109: -6.3138656 | E109: -6.476063 | F109: -7.0279227 | G109: -5.2509967 | H109: -6.9335205 | I109: -6.7025358
A110: current_ratio | B110: 0.83540802 | C110: 0.79198312 | D110: 0.82917214 | E110: 0.81715576 | F110: 0.7444543 | G110: 0.93987788 | H110: 0.76301703 | I110: 0.74294533
A111: debt_to_ebitda | D111: 202.25 | E111: 61.361702 | F111: 21.028571 | G111: 10.161491 | H111: 7.0883055 | I111: 5.6849593
A112: ebitda_ttm | B112: -114000000 | C112: -74000000 | D112: 16000000 | E112: 47000000 | F112: 140000000 | G112: 322000000 | H112: 419000000 | I112: 492000000
A113: fcf_ttm | B113: 213000000 | C113: 244000000 | D113: 295000000 | E113: 333000000 | F113: 429000000 | G113: 464000000 | H113: 488000000 | I113: 562000000
A114: interest_coverage | B114: -6.7058824 | C114: -2.5517241 | D114: 0.34782609 | E114: 0.66197183 | F114: 1.443299 | G114: 2.7058824 | H114: 3.1037037 | I114: 3.3931034
A115: operating_margin | B115: -0.043566363 | C115: -0.038899671 | D115: -0.029362133 | E115: -0.024650233 | F115: -0.015031452 | G115: 0.0013646945 | H115: 0.010112182 | I115: 0.0166615
...

Sheet Stress Scenarios
A1: Stress Scenario Matrix
A2: Assumed covenant 4.5x Debt/EBITDA and 2.0x minimum EBITDA/interest. Red = breach.
A4: Stressed Debt/EBITDA
A5: Ticker | B5: Baseline (as reported) | C5: Revenue -10% | D5: Revenue -20% | E5: EBITDA margin -300bps | F5: Rates +200bps | G5: Inventory +30% (cash funded) | H5: Combined recession
A6: ANF | B6: 0 | C6: 0 | D6: 0 | E6: 0 | F6: 0 | G6: 0 | H6: 0
A7: BBWI | B7: 2.582559 | C7: 2.86951 | D7: 3.2281987 | E7: 3.057589 | F7: 2.582559 | G7: 2.582559 | H7: 3.5971635
A8: BBY | B8: 0.49660153 | C8: 0.55177948 | D8: 0.62075191 | E8: 1.0644691 | F8: 0.49660153 | G8: 0.49660153 | H8: 1.2523166
A9: BURL | B9: 1.4635186 | C9: 1.6261317 | D9: 1.8293982 | E9: 2.0118184 | F9: 1.4635186 | G9: 1.4635186 | H9: 2.3668452
A10: DKS | B10: 1.1048033 | C10: 1.2275592 | D10: 1.3810041 | E10: 1.6588509 | F10: 1.1048033 | G10: 1.1048033 | H10: 1.9515893
A11: GAP | B11: 0.82750971 | C11: 0.91945523 | D11: 1.0343871 | E11: 1.1126025 | F11: 0.82750971 | G11: 0.82750971 | H11: 1.3089442
A12: KSS | B12: 1.0595875 | C12: 1.1773194 | D12: 1.3244843 | E12: 1.64109 | F12: 1.0595875 | G12: 1.0595875 | H12: 1.9306941
A13: M | B13: 1.258148 | C13: 1.3979422 | D13: 1.5726849 | E13: 1.9035394 | F13: 1.258148 | G13: 1.258148 | H13: 2.2394581
A14: ROST | B14: 0.29676403 | C14: 0.32973781 | D14: 0.37095504 | E14: 0.37465259 | F14: 0.29676403 | G14: 0.29676403 | H14: 0.44076775
A15: TGT | B15: 1.9414358 | C15: 2.1571509 | D15: 2.4267947 | E15: 3.2461584 | F15: 1.9414358 | G15: 1.9414358 | H15: 3.8190099
A16: TJX | B16: 0.32484437 | C16: 0.36093819 | D16: 0.40605546 | E16: 0.41073463 | F16: 0.32484437 | G16: 0.32484437 | H16: 0.48321721
A17: W | B17: 5.6849593 | C17: 6.3166215 | D17: 7.1061992 | E17: 26.668574 | F17: 5.6849593 | G17: 5.6849593 | H17: 31.374792
A19: Stressed EBITDA/interest coverage
A20: Ticker | B20: Baseline (as reported) | C20: Revenue -10% | D20: Revenue -20% | E20: EBITDA margin -300bps | F20: Rates +200bps | G20: Inventory +30% (cash funded) | H20: Combined recession
A21: BBWI | B21: 5.1245421 | C21: 4.6120879 | D21: 4.0996337 | E21: 4.3283883 | F21: 4.5256041 | G21: 5.1245421 | H21: 3.2491266
A22: BBY | B22: 51.173913 | C22: 46.056522 | D22: 40.93913 | E22: 23.873913 | F22: 40.804299 | G22: 51.173913 | H22: 16.180794
A23: BURL | B23: 18.265413 | C23: 16.438872 | D23: 14.61233 | E23: 13.287368 | F23: 14.412655 | G23: 18.265413 | H23: 8.9119425
A24: DKS | B24: 24.761674 | C24: 22.285506 | D24: 19.809339 | E24: 16.491403 | F24: 19.442761 | G24: 24.761674 | H24: 11.006632
A25: GAP | B25: 19.597826 | C25: 17.638043 | D25: 15.678261 | E25: 14.576087 | F25: 16.863075 | G25: 19.597826 | H25: 10.660774
A26: KSS | B26: 4.76 | C26: 4.284 | D26: 3.808 | E26: 3.0733455 | F26: 4.5314501 | G26: 4.76 | H26: 2.4869128
A27: M | B27: 20.347368 | C27: 18.312632 | D27: 16.277895 | E27: 13.448632 | F27: 16.200134 | G27: 20.347368 | H27: 9.1013828
A28: ROST | F28: 336.96806 | H28: 226.87685
A29: TGT | B29: 17.762864 | C29: 15.986577 | D29: 14.210291 | E29: 10.623468 | F29: 13.208018 | G29: 17.762864 | H29: 6.7144415
A30: TJX | F30: 307.83972 | H30: 206.94627
A31: W | B31: 3.3931034 | C31: 3.0537931 | D31: 2.7144828 | E31: 0.72331034 | F31: 2.8444239 | G31: 3.3931034 | H31: 0.51539573
A33: Stressed FCF/debt
A34: Ticker | B34: Baseline (as reported) | C34: Revenue -10% | D34: Revenue -20% | E34: EBITDA margin -300bps | F34: Rates +200bps | G34: Inventory +30% (cash funded) | H34: Combined recession
A35: BBWI | B35: 0.25159148 | C35: 0.2283587 | D35: 0.20512593 | E35: 0.21549682 | F35: 0.24409148 | G35: 0.18665929 | H35: 0.11362967
A36: BBY | B36: 1.3729683 | C36: 1.2521471 | D36: 1.1313259 | E36: 0.72841745 | F36: 1.3654683 | G36: -0.06364414 | H36: -0.80024423
A37: BURL | B37: 0.19972222 | C37: 0.15872513 | D37: 0.11772805 | E37: 0.087988995 | F37: 0.19222222 | G37: -0.026245161 | H37: -0.19021404
A38: DKS | B38: 0.21125873 | C38: 0.15695042 | D38: 0.10264211 | E38: 0.029871789 | F38: 0.20375873 | G38: -0.64183287 | H38: -0.88497423
A39: GAP | B39: 0.75335121 | C39: 0.6808445 | D39: 0.6083378 | E39: 0.56756032 | F39: 0.74585121 | G39: 0.33210456 | H39: 0.057922252
A40: KSS | B40: 0.75847152 | C40: 0.70184571 | D40: 0.6452199 | E40: 0.55782408 | F40: 0.75097152 | G40: 0.13186734 | H40: -0.1311217
A41: M | B41: 0.5859375 | C41: 0.53824836 | D41: 0.49055921 | E41: 0.42424836 | F41: 0.5784375 | G41: -0.010238487 | H41: -0.22670798
A42: ROST | B42: 2.585307 | C42: 2.3831262 | D42: 2.1809453 | E42: 2.1649823 | F42: 2.577807 | G42: 1.7081721 | H42: 1.0401248
A43: TGT | B43: 0.19662666 | C43: 0.1657217 | D43: 0.13481674 | E43: 0.072410898 | F43: 0.18912666 | G43: -0.043081414 | H43: -0.20252226
A44: TJX | B44: 1.9083624 | C44: 1.7236585 | D44: 1.5389547 | E44: 1.5221213 | F44: 1.9008624 | G44: 1.1060976 | H44: 0.49323686
A45: W | B45: 0.20092957 | C45: 0.1903754 | D45: 0.17982124 | E45: 0.11788631 | F45: 0.19342957 | G45: 0.19191991 | H45: 0.098001895
A47: Stressed quick ratio
A48: Ticker | B48: Baseline (as reported) | C48: Revenue -10% | D48: Revenue -20% | E48: EBITDA margin -300bps | F48: Rates +200bps | G48: Inventory +30% (cash funded) | H48: Combined recession
A49: ANF | B49: 0.9031335 | C49: 0.9031335 | D49: 0.9031335 | E49: 0.9031335 | F49: 0.9031335 | G49: 0.73958386 | H49: 0.73958386
A50: BBWI | B50: 0.81118373 | C50: 0.81118373 | D50: 0.81118373 | E50: 0.81118373 | F50: 0.81118373 | G50: 0.64081336 | H50: 0.64081336
A51: BBY | B51: 0.4029755 | C51: 0.4029755 | D51: 0.4029755 | E51: 0.4029755 | F51: 0.4029755 | G51: 0.18758497 | H51: 0.18758497
A52: BURL | B52: 0.49290482 | C52: 0.49290482 | D52: 0.49290482 | E52: 0.49290482 | F52: 0.49290482 | G52: 0.29161703 | H52: 0.29161703
A53: DKS | B53: 0.38211569 | C53: 0.38211569 | D53: 0.38211569 | E53: 0.38211569 | F53: 0.38211569 | G53: 0.046490848 | H53: 0.046490848
A54: GAP | B54: 1.0837642 | C54: 1.0837642 | D54: 1.0837642 | E54: 1.0837642 | F54: 1.0837642 | G54: 0.86711479 | H54: 0.86711479
A55: KSS | B55: 0.30628803 | C55: 0.30628803 | D55: 0.30628803 | E55: 0.30628803 | F55: 0.30628803 | G55: -0.046288032 | H55: -0.046288032
A56: M | B56: 0.44137783 | C56: 0.44137783 | D56: 0.44137783 | E56: 0.44137783 | F56: 0.44137783 | G56: 0.13117244 | H56: 0.13117244
A57: ROST | B57: 0.93521803 | C57: 0.93521803 | D57: 0.93521803 | E57: 0.93521803 | F57: 0.93521803 | G57: 0.75350618 | H57: 0.75350618
A58: TGT | B58: 0.29653322 | C58: 0.29653322 | D58: 0.29653322 | E58: 0.29653322 | F58: 0.29653322 | G58: 0.10590693 | H58: 0.10590693
A59: TJX | B59: 0.54181252 | C59: 0.54181252 | D59: 0.54181252 | E59: 0.54181252 | F59: 0.54181252 | G59: 0.36269934 | H59: 0.36269934
A60: W | B60: 0.70590829 | C60: 0.70590829 | D60: 0.70590829 | E60: 0.70590829 | F60: 0.70590829 | G60: 0.69479718 | H60: 0.69479718

Sheet Assumptions
A1: Assumptions & Model Limitations
A2: Nothing in this model is a real negotiated covenant. Every threshold below is an explicit assumption and is the only place it is defined.
A4: Category | B4: Assumption | C4: Value | D4: Rationale
A5: Credit policy | B5: Max Debt/EBITDA (assumed covenant) | C5: 4.5 | D5: Illustrative of total-leverage maintenance tests in public retail term loans. Real agreements are private; this is not one of them.
A6: Credit policy | B6: Min EBITDA/interest coverage | C6: 2 | D6: Typical minimum coverage test.
A7: Credit policy | B7: Min current ratio | C7: 1 | D7: Working-capital liquidity floor.
A8: Credit policy | B8: Min FCF/debt | C8: 0.05 | D8: Below this, the company cannot meaningfully deleverage from cash flow.
A9: Credit policy | B9: Refinancing concentration trigger | C9: 0.25 | D9: Share of total debt maturing within 12 months that warrants a flag.
A10: Altman | B10: Z" distress threshold | C10: 1.1 | D10: Z" (non-manufacturer revision) is used, not the 1968 manufacturing Z.
A11: Altman | B11: Z" safe threshold | C11: 2.6 | D11: Above this = safe zone.
A12: Stress | B12: Floating-rate share of debt | C12: 0.5 | D12: Filings rarely give a clean fixed/floating split; assumed, and only this share reprices in the rate scenario.
A13: Stress | B13: Inventory build | C13: 0.3 | D13: Assumed cash-funded, so current assets are unchanged and the quick ratio absorbs the hit.
A14: Stress | B14: EBITDA-to-FCF passthrough | C14: 0.8 | D14: A sales decline releases working capital, cushioning cash flow, so less than 100% of an EBITDA fall reaches FCF in year one.
A15: Stress | B15: Cash tax rate | C15: 0.25 | D15: Converts the pre-tax earnings shock into an after-tax cash-flow shock.
A16: Early warning | B16: Leverage rise (turns YoY) | C16: 0.75 | D16: Trend trigger: still compliant, but moving the wrong way.
... A19: Scorecard | B19: Min data coverage for a grade | C19: 0.6 | D19: Below this share of scorecard weight the grade is suppressed as NR, so a thin data set cannot produce a flattering grade.
A21: Scorecard weights
A22: Metric | B22: Direction | C22: Good / weak band | D22: Weight
A23: debt_to_ebitda | B23: lower better | C23: 2.0 / 4.0 | D23: 0.25
A24: net_debt_to_ebitda | B24: lower better | C24: 1.5 / 3.5 | D24: 0.1
A25: interest_coverage | B25: higher better | C25: 6.0 / 3.0 | D25: 0.2
A26: fcf_to_debt | B26: higher better | C26: 0.2 / 0.08 | D26: 0.15
A27: current_ratio | B27: higher better | C27: 1.5 / 1.0 | D27: 0.1
A28: quick_ratio | B28: higher better | C28: 0.8 / 0.4 | D28: 0.05
A29: altman_z_double_prime | B29: higher better | C29: 2.6 / 1.1 | D29: 0.15
A31: Known limitations
A32: - Altman Z" was calibrated on non-manufacturers but not on modern e-commerce or omni-channel retail; treat the zone as a ranking, not a verdict.
A33: - The PD proxy is a rules-based scorecard. It was NOT fit to historical default data, so its Low/Medium/High bands are relative risk ranking, not probabilities.
A34: - Covenant thresholds are assumptions. Real agreements often use net leverage, adjusted EBITDA with addbacks, and step-downs, all of which would change headroom.
A35: - Operating lease liabilities are excluded from total debt. Rating agencies often capitalise them, which would raise leverage materially for retailers.
A36: - EBITDA is unadjusted: no addbacks for impairments, restructuring or stock compensation, so it is more conservative than a credit agreement's definition.
A37: - Where a company discloses only net interest quarterly, coverage is computed on a net basis and flagged in the interest_basis column.
A38: - The model uses the latest filed quarter, which lags the market by up to a quarter; it cannot see events since the last filing.

Sheet Data Quality
A1: Extraction Audit
A2: Which XBRL concept fed each metric, how much history it covers, and how much had to be reconstructed from year-to-date disclosures.
A4: Input provenance by company
A5: Ticker | B5: Debt source | C5: EBIT source | D5: Interest basis | E5: Scorecard coverage | F5: Balance sheet as of
A6: W | B6: current + noncurrent legs | C6: reported | D6: net of interest income | E6: 1 | F6: 2026-06-30
A7: BBWI | B7: current + noncurrent legs | C7: reported | D7: gross | E7: 1 | F7: 2026-05-02
A8: TGT | B8: current + noncurrent legs | C8: reported | D8: gross | E8: 1 | F8: 2026-05-02
A9: BURL | B9: current + noncurrent legs | C9: derived: pretax less net interest | D9: gross | E9: 1 | F9: 2026-05-02
A10: M | B10: current + noncurrent legs | C10: reported | D10: net of interest income | E10: 1 | F10: 2026-05-02
A11: DKS | B11: combined debt tag | C11: reported | D11: gross | E11: 1 | F11: 2026-05-02
A12: KSS | B12: current + noncurrent legs | C12: reported | D12: net of interest income | E12: 1 | F12: 2026-05-02
A13: GAP | B13: current + noncurrent legs | C13: reported | D13: gross | E13: 1 | F13: 2026-05-02
A14: BBY | B14: current + noncurrent legs | C14: reported | D14: gross | E14: 1 | F14: 2026-05-02
A15: TJX | B15: current + noncurrent legs | C15: derived: pretax less net interest | D15: net of interest income | E15: 1 | F15: 2026-05-02
A16: ROST | B16: current + noncurrent legs | C16: reported | D16: net of interest income | E16: 1 | F16: 2026-05-02
A17: ANF | B17: nil (debt caption removed after full repayment) | C17: reported | D17: net of interest income | E17: 1 | F17: 2026-05-02
A19: Concept-level extraction log
A20: Ticker | B20: Metric | C20: Concept(s) used | D20: Quarters | E20: First period | F20: Last period | G20: Share de-cumulated
A21: ANF | B21: capex | C21: PaymentsToAcquirePropertyPlantAndEquipment | D21: 67 | E21: 2009-10-31 | F21: 2026-05-02 | G21: 0.746
A22: ANF | B22: cash | C22: CashAndCashEquivalentsAtCarryingValue | D22: 71 | E22: 2008-02-02 | F22: 2026-05-02 | G22: 0
A23: ANF | B23: current_assets | C23: AssetsCurrent | D23: 66 | E23: 2010-01-30 | F23: 2026-05-02 | G23: 0
A24: ANF | B24: current_liabilities | C24: LiabilitiesCurrent | D24: 66 | E24: 2010-01-30 | F24: 2026-05-02 | G24: 0
A25: ANF | B25: debt_current | C25: LongTermDebtCurrent | D25: 9 | E25: 2013-02-02 | F25: 2020-05-02 | G25: 0
A26: ANF | B26: debt_noncurrent | C26: LongTermDebtNoncurrent | D26: 59 | E26: 2010-01-30 | F26: 2025-02-01 | G26: 0
A27: ANF | B27: debt_total_reported | C27: DebtLongtermAndShorttermCombinedAmount,LongTermDebt | D27: 9 | E27: 2013-02-02 | F27: 2018-11-03 | G27: 0
A28: ANF | B28: depreciation_amortization | C28: DepreciationAndAmortization | D28: 67 | E28: 2009-10-31 | F28: 2026-05-02 | G28: 0.687
A29: ANF | B29: finance_lease_current | D29: 0
A30: ANF | B30: finance_lease_noncurrent | D30: 0
A31: ANF | B31: interest_expense | C31: InterestExpense,FinancingInterestExpense | D31: 22 | E31: 2010-07-31 | F31: 2024-08-03 | G31: 0.227
A32: ANF | B32: interest_income | D32: 0
A33: ANF | B33: inventory | C33: InventoryNet | D33: 66 | E33: 2010-01-30 | F33: 2026-05-02 | G33: 0
A34: ANF | B34: net_interest_income | C34: InterestIncomeExpenseNet | D34: 68 | E34: 2009-08-01 | F34: 2026-05-02 | G34: 0.25
A35: ANF | B35: operating_cash_flow | C35: NetCashProvidedByUsedInOperatingActivities | D35: 67 | E35: 2009-10-31 | F35: 2026-05-02 | G35: 0.746
A36: ANF | B36: operating_income | C36: OperatingIncomeLoss | D36: 68 | E36: 2009-08-01 | F36: 2026-05-02 | G36: 0.25
A37: ANF | B37: operating_lease_liability | C37: OperatingLeaseLiabilityNoncurrent | D37: 31 | E37: 2019-02-02 | F37: 2026-05-02 | G37: 0
A38: ANF | B38: pretax_income | C38: IncomeLossFromContinuingOperationsBeforeIncomeTaxesExtraordinaryItemsNoncontrollingInterest,IncomeLossFromContinuingOperationsBeforeIncomeTaxesMinorityInterestAndIncomeLossFromEquityMethodInvestments | D38: 68 | E38: 2009-08-01 | F38: 2026-05-02 | G38: 0.25
A39: ANF | B39: retained_earnings | C39: RetainedEarningsAccumulatedDeficit | D39: 66 | E39: 2010-01-30 | F39: 2026-05-02 | G39: 0
A40: ANF | B40: revenue | C40: Revenues,SalesRevenueNet | D40: 68 | E40: 2009-08-01 | F40: 2026-05-02 | G40: 0.103
A41: ANF | B41: short_term_borrowings | C41: ShortTermBorrowings | D41: 24 | E41: 2012-01-28 | F41: 2020-05-02 | G41: 0
A42: ANF | B42: short_term_investments | D42: 0
A43: ANF | B43: stockholders_equity | C43: StockholdersEquity,StockholdersEquityIncludingPortionAttributableToNoncontrollingInterest | D43: 68 | E43: 2008-02-02 | F43: 2026-05-02 | G43: 0
A44: ANF | B44: total_assets | C44: Assets | D44: 66 | E44: 2010-01-30 | F44: 2026-05-02 | G44: 0
A45: ANF | B45: total_equity_incl_nci | C45: StockholdersEquityIncludingPortionAttributableToNoncontrollingInterest,StockholdersEquity | D45: 68 | E45: 2008-02-02 | F45: 2026-05-02 | G45: 0
A46: ANF | B46: total_liabilities | D46: 0
A47: BBWI | B47: capex | C47: PaymentsToAcquirePropertyPlantAndEquipment | D47: 71 | E47: 2008-11-01 | F47: 2026-05-02 | G47: 0.746
A48: BBWI | B48: cash | C48: CashAndCashEquivalentsAtCarryingValue | D48: 74 | E48: 2007-02-03 | F48: 2026-05-02 | G48: 0
A49: BBWI | B49: current_assets | C49: AssetsCurrent | D49: 72 | E49: 2008-08-02 | F49: 2026-05-02 | G49: 0
A50: BBWI | B50: current_liabilities | C50: LiabilitiesCurrent | D50: 72 | E50: 2008-08-02 | F50: 2026-05-02 | G50: 0
A51: BBWI | B51: debt_current | C51: LongTermDebtCurrent,DebtCurrent | D51: 60 | E51: 2009-08-01 | F51: 2026-05-02 | G51: 0
A52: BBWI | B52: debt_noncurrent | C52: LongTermDebtNoncurrent | D52: 72 | E52: 2008-08-02 | F52: 2026-05-02 | G52: 0
A53: BBWI | B53: debt_total_reported | C53: DebtLongtermAndShorttermCombinedAmount,LongTermDebt | D53: 68 | E53: 2009-08-01 | F53: 2026-05-02 | G53: 0
A54: BBWI | B54: depreciation_amortization | C54: DepreciationAmortizationAndAccretionNet,DepreciationAndAmortization,Depreciation | D54: 71 | E54: 2008-11-01 | F54: 2026-05-02 | G54: 0.535
A55: BBWI | B55: finance_lease_current | C55: FinanceLeaseLiabilityCurrent | D55: 9 | E55: 2018-05-05 | F55: 2021-01-30 | G55: 0
A56: BBWI | B56: finance_lease_noncurrent | C56: FinanceLeaseLiabilityNoncurrent | D56: 9 | E56: 2018-05-05 | F56: 2021-01-30 | G56: 0
A57: BBWI | B57: interest_expense | C57: InterestExpense | D57: 72 | E57: 2008-08-02 | F57: 2026-05-02 | G57: 0.25
A58: BBWI | B58: interest_income | C58: InvestmentIncomeInterest | D58: 12 | E58: 2008-08-02 | F58: 2011-04-30 | G58: 0.25
A59: BBWI | B59: inventory | C59: InventoryNet | D59: 72 | E59: 2008-08-02 | F59: 2026-05-02 | G59: 0
A60: BBWI | B60: net_interest_income | D60: 0
A61: BBWI | B61: operating_cash_flow | C61: NetCashProvidedByUsedInOperatingActivities | D61: 71 | E61: 2008-11-01 | F61: 2026-05-02 | G61: 0.746
A62: BBWI | B62: operating_income | C62: OperatingIncomeLoss | D62: 72 | E62: 2008-08-02 | F62: 2026-05-02 | G62: 0.056
A63: BBWI | B63: operating_lease_liability | C63: OperatingLeaseLiabilityNoncurrent | D63: 33 | E63: 2018-05-05 | F63: 2026-05-02 | G63: 0
A64: BBWI | B64: pretax_income | C64: IncomeLossFromContinuingOperationsBeforeIncomeTaxesExtraordinaryItemsNoncontrollingInterest,IncomeLossFromContinuingOperationsBeforeIncomeTaxesMinorityInterestAndIncomeLossFromEquityMethodInvestments | D64: 70 | E64: 2008-08-02 | F64: 2026-05-02 | G64: 0.043
A65: BBWI | B65: retained_earnings | C65: RetainedEarningsAccumulatedDeficit | D65: 72 | E65: 2008-08-02 | F65: 2026-05-02 | G65: 0
A66: BBWI | B66: revenue | C66: RevenueFromContractWithCustomerExcludingAssessedTax,SalesRevenueNet | D66: 72 | E66: 2008-08-02 | F66: 2026-05-02 | G66: 0.056
A67: BBWI | B67: short_term_borrowings | D67: 0
A68: BBWI | B68: short_term_investments | D68: 0
A69: BBWI | B69: stockholders_equity | C69: StockholdersEquity,StockholdersEquityIncludingPortionAttributableToNoncontrollingInterest | D69: 74 | E69: 2007-02-03 | F69: 2026-05-02 | G69: 0
A70: BBWI | B70: total_assets | C70: Assets | D70: 72 | E70: 2008-08-02 | F70: 2026-05-02 | G70: 0
A71: BBWI | B71: total_equity_incl_nci | C71: StockholdersEquityIncludingPortionAttributableToNoncontrollingInterest | D71: 74 | E71: 2007-02-03 | F71: 2026-05-02 | G71: 0
A72: BBWI | B72: total_liabilities | D72: 0
A73: BBY | B73: capex | C73: PaymentsToAcquirePropertyPlantAndEquipment | D73: 72 | E73: 2008-11-29 | F73: 2026-05-02 | G73: 0.736
A74: BBY | B74: cash | C74: CashAndCashEquivalentsAtCarryingValue | D74: 81 | E74: 2007-03-03 | F74: 2026-05-02 | G74: 0
A75: BBY | B75: current_assets | C75: AssetsCurrent | D75: 75 | E75: 2008-08-30 | F75: 2026-05-02 | G75: 0
A76: BBY | B76: current_liabilities | C76: LiabilitiesCurrent | D76: 75 | E76: 2008-08-30 | F76: 2026-05-02 | G76: 0
A77: BBY | B77: debt_current | C77: LongTermDebtAndCapitalLeaseObligationsCurrent,LongTermDebtCurrent | D77: 76 | E77: 2008-08-30 | F77: 2026-05-02 | G77: 0
A78: BBY | B78: debt_noncurrent | C78: LongTermDebtAndCapitalLeaseObligations,LongTermDebtNoncurrent | D78: 76 | E78: 2008-08-30 | F78: 2026-05-02 | G78: 0
A79: BBY | B79: debt_total_reported | C79: LongTermDebt,DebtAndCapitalLeaseObligations | D79: 65 | E79: 2009-08-29 | F79: 2026-05-02 | G79: 0
A80: BBY | B80: depreciation_amortization | C80: DepreciationDepletionAndAmortization,Depreciation | D80: 72 | E80: 2008-11-29 | F80: 2026-05-02 | G80: 0.736
A81: BBY | B81: finance_lease_current | C81: FinanceLeaseLiabilityCurrent | D81: 10 | E81: 2019-05-04 | F81: 2026-01-31 | G81: 0
A82: BBY | B82: finance_lease_noncurrent | C82: FinanceLeaseLiabilityNoncurrent | D82: 10 | E82: 2019-05-04 | F82: 2026-01-31 | G82: 0
A83: BBY | B83: interest_expense | C83: InterestExpenseNonoperating,InterestExpense | D83: 73 | E83: 2008-08-30 | F83: 2026-05-02 | G83: 0.219
A84: BBY | B84: interest_income | D84: 0
A85: BBY | B85: inventory | C85: InventoryNet | D85: 75 | E85: 2008-08-30 | F85: 2026-05-02 | G85: 0
A86: BBY | B86: net_interest_income | D86: 0
A87: BBY | B87: operating_cash_flow | C87: NetCashProvidedByUsedInOperatingActivities | D87: 72 | E87: 2008-11-29 | F87: 2026-05-02 | G87: 0.736
A88: BBY | B88: operating_income | C88: OperatingIncomeLoss | D88: 75 | E88: 2008-08-30 | F88: 2026-05-02 | G88: 0.093
A89: BBY | B89: operating_lease_liability | C89: OperatingLeaseLiabilityNoncurrent | D89: 30 | E89: 2019-02-03 | F89: 2026-05-02 | G89: 0
A90: BBY | B90: pretax_income | C90: IncomeLossFromContinuingOperationsBeforeIncomeTaxesExtraordinaryItemsNoncontrollingInterest,IncomeLossFromContinuingOperationsBeforeIncomeTaxesMinorityInterestAndIncomeLossFromEquityMethodInvestments | D90: 73 | E90: 2008-08-30 | F90: 2026-05-02 | G90: 0.219
A91: BBY | B91: retained_earnings | C91: RetainedEarningsAccumulatedDeficit | D91: 77 | E91: 2008-08-30 | F91: 2026-05-02 | G91: 0
A92: BBY | B92: revenue | C92: RevenueFromContractWithCustomerIncludingAssessedTax,SalesRevenueNet | D92: 75 | E92: 2008-08-30 | F92: 2026-05-02 | G92: 0.093
A93: BBY | B93: short_term_borrowings | C93: ShortTermBorrowings | D93: 32 | E93: 2008-08-30 | F93: 2021-07-31 | G93: 0
A94: BBY | B94: short_term_investments | C94: ShortTermInvestments | D94: 48 | E94: 2008-11-29 | F94: 2021-05-01 | G94: 0
A95: BBY | B95: stockholders_equity | C95: StockholdersEquity,StockholdersEquityIncludingPortionAttributableToNoncontrollingInterest | D95: 79 | E95: 2007-03-03 | F95: 2026-05-02 | G95: 0
A96: BBY | B96: total_assets | C96: Assets | D96: 75 | E96: 2008-08-30 | F96: 2026-05-02 | G96: 0
A97: BBY | B97: total_equity_incl_nci | C97: StockholdersEquityIncludingPortionAttributableToNoncontrollingInterest | D97: 79 | E97: 2007-03-03 | F97: 2026-05-02 | G97: 0
A98: BBY | B98: total_liabilities | D98: 0
A99: BURL | B99: capex | C99: PaymentsToAcquirePropertyPlantAndEquipment | D99: 52 | E99: 2013-05-04 | F99: 2026-05-02 | G99: 0.731
A100: BURL | B100: cash | C100: CashAndCashEquivalentsAtCarryingValue | D100: 62 | E100: 2011-01-28 | F100: 2026-05-02 | G100: 0
A101: BURL | B101: current_assets | C101: AssetsCurrent | D101: 55 | E101: 2012-10-27 | F101: 2026-05-02 | G101: 0
A102: BURL | B102: current_liabilities | C102: LiabilitiesCurrent | D102: 55 | E102: 2012-10-27 | F102: 2026-05-02 | G102: 0
...
